safepull/__init__.py
safepull/__main__.py
safepull/models.py
safepull/safepull.py
safepull-2.2.2.dist-info/LICENSE
safepull-2.2.2.dist-info/METADATA
safepull-2.2.2.dist-info/WHEEL
safepull-2.2.2.dist-info/entry_points.txt
safepull-2.2.2.dist-info/RECORD
