Metadata-Version: 2.1
Name: safepull
Version: 2.2.2
Summary: A CLI tool for downloading and extracting packages from PyPI without interfacing with setup.py.
Home-page: https://pypi.org/project/safepull/
License: MIT
Author: Rem
Author-email: 128343390+import-pandas-as-numpy@users.noreply.github.com
Requires-Python: >=3.10,<4.0
Classifier: License :: OSI Approved :: MIT License
Classifier: Programming Language :: Python :: 3
Classifier: Programming Language :: Python :: 3.10
Classifier: Programming Language :: Python :: 3.11
Classifier: Programming Language :: Python :: 3.12
Requires-Dist: humanize (>=4.9.0,<5.0.0)
Requires-Dist: requests (>=2.31.0,<3.0.0)
Requires-Dist: rich (>=13.4.2,<14.0.0)
Project-URL: Repository, https://github.com/import-pandas-as-numpy/safepull
